cepimose/__init__.py
cepimose/commands.py
cepimose/data.py
cepimose/enums.py
cepimose/parser.py
cepimose/types.py
cepimose-0.1.34.dist-info/METADATA
cepimose-0.1.34.dist-info/WHEEL
cepimose-0.1.34.dist-info/top_level.txt
cepimose-0.1.34.dist-info/RECORD
