Metadata-Version: 2.1
Name: cepimose
Version: 0.1.34
Summary: A small example package to get raw data from NIJZ vaccinations dashboard
Home-page: https://github.com/sledilnik/py-cepimose
Author: sledilnik.org
Author-email: info@sledilnik.org
License: UNKNOWN
Project-URL: Bug Tracker, https://github.com/sledilnik/py-cepimose/issues
Platform: UNKNOWN
Classifier: Programming Language :: Python :: 3
Classifier: License :: OSI Approved :: MIT License
Classifier: Operating System :: OS Independent
Requires-Python: >=3.6
Requires-Dist: requests
